MANIFEST.in
README.rst
setup.cfg
setup.py
puresec_cli/__init__.py
puresec_cli/__main__.py
puresec_cli/cli.py
puresec_cli/stats.py
puresec_cli/utils.py
puresec_cli.egg-info/PKG-INFO
puresec_cli.egg-info/SOURCES.txt
puresec_cli.egg-info/dependency_links.txt
puresec_cli.egg-info/entry_points.txt
puresec_cli.egg-info/requires.txt
puresec_cli.egg-info/top_level.txt
puresec_cli/actions/__init__.py
puresec_cli/actions/base.py
puresec_cli/actions/generate_roles/__init__.py
puresec_cli/actions/generate_roles/generate_roles.py
puresec_cli/actions/generate_roles/frameworks/__init__.py
puresec_cli/actions/generate_roles/frameworks/base.py
puresec_cli/actions/generate_roles/frameworks/serverless.py
puresec_cli/actions/generate_roles/providers/__init__.py
puresec_cli/actions/generate_roles/providers/aws.py
puresec_cli/actions/generate_roles/providers/aws_api.py
puresec_cli/actions/generate_roles/providers/base.py
puresec_cli/actions/generate_roles/runtimes/__init__.py
puresec_cli/actions/generate_roles/runtimes/base.py
puresec_cli/actions/generate_roles/runtimes/aws/__init__.py
puresec_cli/actions/generate_roles/runtimes/aws/base.py
puresec_cli/actions/generate_roles/runtimes/aws/base_api.py
puresec_cli/actions/generate_roles/runtimes/aws/nodejs.py
puresec_cli/actions/generate_roles/runtimes/aws/nodejs_api.py
puresec_cli/actions/generate_roles/runtimes/aws/python.py
puresec_cli/actions/generate_roles/runtimes/aws/python_api.py
puresec_cli/frameworks/__init__.py
puresec_cli/frameworks/serverless.py
puresec_cli/providers/__init__.py
puresec_cli/providers/aws.py
puresec_cli/resources/list-dependencies.py
puresec_cli/resources/package-lock.json
puresec_cli/resources/node_modules/.bin/babylon
puresec_cli/resources/node_modules/.bin/dependency-tree
puresec_cli/resources/node_modules/.bin/detective-amd
puresec_cli/resources/node_modules/.bin/errno
puresec_cli/resources/node_modules/.bin/escodegen
puresec_cli/resources/node_modules/.bin/esgenerate
puresec_cli/resources/node_modules/.bin/esparse
puresec_cli/resources/node_modules/.bin/esvalidate
puresec_cli/resources/node_modules/.bin/filing-cabinet
puresec_cli/resources/node_modules/.bin/gonzales
