Metadata-Version: 1.0
Name: puresec-cli
Version: 1.2.1
Summary: PureSec CLI tools for improving the security of your serverless applications.
Home-page: https://github.com/puresec/puresec-cli
Author: PureSec
Author-email: support@puresec.io
License: UNKNOWN
Platform: UNKNOWN
